<root><test><Config>
<query>Select * from [OrderDetails$]
keycols:ID, OrderID
</query>
</Config>
<row>
<ID>27</ID>
<OrderID>30</OrderID>
<Product>Northwind Traders Beer</Product>
<Quantity>100</Quantity>
<UnitPrice>14</UnitPrice>
<Discount>0</Discount>
<StatusID>Invoiced</StatusID>
<DateAllocated>NULL</DateAllocated>
<PurchaseOrderID>96</PurchaseOrderID>
<InventoryID>83</InventoryID>
</row>
<row>
<ID>28</ID>
<OrderID>30</OrderID>
<Product>Northwind Traders Dried Plums</Product>
<Quantity>30</Quantity>
<UnitPrice>3.5</UnitPrice>
<Discount>0</Discount>
<StatusID>Invoiced</StatusID>
<DateAllocated>NULL</DateAllocated>
<PurchaseOrderID>NULL</PurchaseOrderID>
<InventoryID>63</InventoryID>
</row>
<row>
<ID>29</ID>
<OrderID>31</OrderID>
<Product>Northwind Traders Dried Pears</Product>
<Quantity>10</Quantity>
<UnitPrice>30</UnitPrice>
<Discount>0</Discount>
<StatusID>Invoiced</StatusID>
<DateAllocated>NULL</DateAllocated>
<PurchaseOrderID>NULL</PurchaseOrderID>
<InventoryID>64</InventoryID>
</row>
<row>
<ID>30</ID>
<OrderID>31</OrderID>
<Product>Northwind Traders Dried Apples</Product>
<Quantity>10</Quantity>
<UnitPrice>53</UnitPrice>
<Discount>0</Discount>
<StatusID>Invoiced</StatusID>
<DateAllocated>NULL</DateAllocated>
<PurchaseOrderID>NULL</PurchaseOrderID>
<InventoryID>65</InventoryID>
</row>
<row>
<ID>31</ID>
<OrderID>31</OrderID>
<Product>Northwind Traders Dried Plums</Product>
<Quantity>10</Quantity>
<UnitPrice>3.5</UnitPrice>
<Discount>0</Discount>
<StatusID>Invoiced</StatusID>
<DateAllocated>NULL</DateAllocated>
<PurchaseOrderID>NULL</PurchaseOrderID>
<InventoryID>66</InventoryID>
</row>
<row>
<ID>32</ID>
<OrderID>32</OrderID>
<Product>Northwind Traders Chai</Product>
<Quantity>15</Quantity>
<UnitPrice>18</UnitPrice>
<Discount>0</Discount>
<StatusID>Invoiced</StatusID>
<DateAllocated>NULL</DateAllocated>
<PurchaseOrderID>NULL</PurchaseOrderID>
<InventoryID>67</InventoryID>
</row>
<row>
<ID>33</ID>
<OrderID>32</OrderID>
<Product>Northwind Traders Coffee</Product>
<Quantity>20</Quantity>
<UnitPrice>46</UnitPrice>
<Discount>0</Discount>
<StatusID>Invoiced</StatusID>
<DateAllocated>NULL</DateAllocated>
<PurchaseOrderID>NULL</PurchaseOrderID>
<InventoryID>68</InventoryID>
</row>
<row>
<ID>34</ID>
<OrderID>34</OrderID>
<Product>Northwind Traders Chocolate Biscuits Mix</Product>
<Quantity>30</Quantity>
<UnitPrice>9.2</UnitPrice>
<Discount>0</Discount>
<StatusID>Invoiced</StatusID>
<DateAllocated>NULL</DateAllocated>
<PurchaseOrderID>97</PurchaseOrderID>
<InventoryID>81</InventoryID>
</row>
<row>
<ID>35</ID>
<OrderID>34</OrderID>
<Product>Northwind Traders Chocolate Biscuits Mix</Product>
<Quantity>20</Quantity>
<UnitPrice>9.2</UnitPrice>
<Discount>0</Discount>
<StatusID>Invoiced</StatusID>
<DateAllocated>NULL</DateAllocated>
<PurchaseOrderID>NULL</PurchaseOrderID>
<InventoryID>69</InventoryID>
</row>
<row>
<ID>36</ID>
<OrderID>35</OrderID>
<Product>Northwind Traders Chocolate</Product>
<Quantity>10</Quantity>
<UnitPrice>12.75</UnitPrice>
<Discount>0</Discount>
<StatusID>Invoiced</StatusID>
<DateAllocated>NULL</DateAllocated>
<PurchaseOrderID>NULL</PurchaseOrderID>
<InventoryID>70</InventoryID>
</row>
<row>
<ID>37</ID>
<OrderID>36</OrderID>
<Product>Northwind Traders Clam Chowder</Product>
<Quantity>200</Quantity>
<UnitPrice>9.65</UnitPrice>
<Discount>0</Discount>
<StatusID>Invoiced</StatusID>
<DateAllocated>NULL</DateAllocated>
<PurchaseOrderID>98</PurchaseOrderID>
<InventoryID>79</InventoryID>
</row>
<row>
<ID>38</ID>
<OrderID>37</OrderID>
<Product>Northwind Traders Curry Sauce</Product>
<Quantity>17</Quantity>
<UnitPrice>40</UnitPrice>
<Discount>0</Discount>
<StatusID>Invoiced</StatusID>
<DateAllocated>NULL</DateAllocated>
<PurchaseOrderID>NULL</PurchaseOrderID>
<InventoryID>71</InventoryID>
</row>
<row>
<ID>39</ID>
<OrderID>38</OrderID>
<Product>Northwind Traders Coffee</Product>
<Quantity>300</Quantity>
<UnitPrice>46</UnitPrice>
<Discount>0</Discount>
<StatusID>Invoiced</StatusID>
<DateAllocated>NULL</DateAllocated>
<PurchaseOrderID>99</PurchaseOrderID>
<InventoryID>77</InventoryID>
</row>
<row>
<ID>40</ID>
<OrderID>39</OrderID>
<Product>Northwind Traders Chocolate</Product>
<Quantity>100</Quantity>
<UnitPrice>12.75</UnitPrice>
<Discount>0</Discount>
<StatusID>Invoiced</StatusID>
<DateAllocated>NULL</DateAllocated>
<PurchaseOrderID>100</PurchaseOrderID>
<InventoryID>75</InventoryID>
</row>
<row>
<ID>41</ID>
<OrderID>40</OrderID>
<Product>Northwind Traders Green Tea</Product>
<Quantity>200</Quantity>
<UnitPrice>2.99</UnitPrice>
<Discount>0</Discount>
<StatusID>Invoiced</StatusID>
<DateAllocated>NULL</DateAllocated>
<PurchaseOrderID>101</PurchaseOrderID>
<InventoryID>73</InventoryID>
</row>
<row>
<ID>42</ID>
<OrderID>41</OrderID>
<Product>Northwind Traders Coffee</Product>
<Quantity>300</Quantity>
<UnitPrice>46</UnitPrice>
<Discount>0</Discount>
<StatusID>Allocated</StatusID>
<DateAllocated>NULL</DateAllocated>
<PurchaseOrderID>102</PurchaseOrderID>
<InventoryID>104</InventoryID>
</row>
<row>
<ID>43</ID>
<OrderID>42</OrderID>
<Product>Northwind Traders Boysenberry Spread</Product>
<Quantity>10</Quantity>
<UnitPrice>23</UnitPrice>
<Discount>0</Discount>
<StatusID>Invoiced</StatusID>
<DateAllocated>NULL</DateAllocated>
<PurchaseOrderID>NULL</PurchaseOrderID>
<InventoryID>84</InventoryID>
</row>
<row>
<ID>44</ID>
<OrderID>42</OrderID>
<Product>Northwind Traders Cajun Seasoning</Product>
<Quantity>10</Quantity>
<UnitPrice>22</UnitPrice>
<Discount>0</Discount>
<StatusID>Invoiced</StatusID>
<DateAllocated>NULL</DateAllocated>
<PurchaseOrderID>NULL</PurchaseOrderID>
<InventoryID>85</InventoryID>
</row>
<row>
<ID>45</ID>
<OrderID>42</OrderID>
<Product>Northwind Traders Chocolate Biscuits Mix</Product>
<Quantity>10</Quantity>
<UnitPrice>9.2</UnitPrice>
<Discount>0</Discount>
<StatusID>Invoiced</StatusID>
<DateAllocated>NULL</DateAllocated>
<PurchaseOrderID>103</PurchaseOrderID>
<InventoryID>110</InventoryID>
</row>
<row>
<ID>46</ID>
<OrderID>43</OrderID>
<Product>Northwind Traders Dried Plums</Product>
<Quantity>20</Quantity>
<UnitPrice>3.5</UnitPrice>
<Discount>0</Discount>
<StatusID>Allocated</StatusID>
<DateAllocated>NULL</DateAllocated>
<PurchaseOrderID>NULL</PurchaseOrderID>
<InventoryID>86</InventoryID>
</row>
<row>
<ID>47</ID>
<OrderID>43</OrderID>
<Product>Northwind Traders Green Tea</Product>
<Quantity>50</Quantity>
<UnitPrice>2.99</UnitPrice>
<Discount>0</Discount>
<StatusID>Allocated</StatusID>
<DateAllocated>NULL</DateAllocated>
<PurchaseOrderID>NULL</PurchaseOrderID>
<InventoryID>87</InventoryID>
</row>
<row>
<ID>48</ID>
<OrderID>44</OrderID>
<Product>Northwind Traders Chai</Product>
<Quantity>25</Quantity>
<UnitPrice>18</UnitPrice>
<Discount>0</Discount>
<StatusID>Allocated</StatusID>
<DateAllocated>NULL</DateAllocated>
<PurchaseOrderID>NULL</PurchaseOrderID>
<InventoryID>88</InventoryID>
</row>
<row>
<ID>49</ID>
<OrderID>44</OrderID>
<Product>Northwind Traders Coffee</Product>
<Quantity>25</Quantity>
<UnitPrice>46</UnitPrice>
<Discount>0</Discount>
<StatusID>Allocated</StatusID>
<DateAllocated>NULL</DateAllocated>
<PurchaseOrderID>NULL</PurchaseOrderID>
<InventoryID>89</InventoryID>
</row>
<row>
<ID>50</ID>
<OrderID>44</OrderID>
<Product>Northwind Traders Green Tea</Product>
<Quantity>25</Quantity>
<UnitPrice>2.99</UnitPrice>
<Discount>0</Discount>
<StatusID>Allocated</StatusID>
<DateAllocated>NULL</DateAllocated>
<PurchaseOrderID>NULL</PurchaseOrderID>
<InventoryID>90</InventoryID>
</row>
<row>
<ID>51</ID>
<OrderID>45</OrderID>
<Product>Northwind Traders Clam</Product>
<Quantity>50</Quantity>
<UnitPrice>9.65</UnitPrice>
<Discount>0</Discount>
<StatusID>Invoiced</StatusID>
<DateAllocated>NULL</DateAllocated>
<PurchaseOrderID>104</PurchaseOrderID>
<InventoryID>116</InventoryID>
</row>
<row>
<ID>52</ID>
<OrderID>45</OrderID>
<Product>Northwind Traders Crab Meat</Product>
<Quantity>50</Quantity>
<UnitPrice>18.4</UnitPrice>
<Discount>0</Discount>
<StatusID>Invoiced</StatusID>
<DateAllocated>NULL</DateAllocated>
<PurchaseOrderID>NULL</PurchaseOrderID>
<InventoryID>91</InventoryID>
</row>
<row>
<ID>53</ID>
<OrderID>46</OrderID>
<Product>Northwind Traders Ravioli</Product>
<Quantity>100</Quantity>
<UnitPrice>19.5</UnitPrice>
<Discount>0</Discount>
<StatusID>Invoiced</StatusID>
<DateAllocated>NULL</DateAllocated>
<PurchaseOrderID>105</PurchaseOrderID>
<InventoryID>101</InventoryID>
</row>
<row>
<ID>54</ID>
<OrderID>46</OrderID>
<Product>Northwind Traders Mozzarella</Product>
<Quantity>50</Quantity>
<UnitPrice>34.8</UnitPrice>
<Discount>0</Discount>
<StatusID>Invoiced</StatusID>
<DateAllocated>NULL</DateAllocated>
<PurchaseOrderID>106</PurchaseOrderID>
<InventoryID>114</InventoryID>
</row>
<row>
<ID>55</ID>
<OrderID>47</OrderID>
<Product>Northwind Traders Beer</Product>
<Quantity>300</Quantity>
<UnitPrice>14</UnitPrice>
<Discount>0</Discount>
<StatusID>Invoiced</StatusID>
<DateAllocated>NULL</DateAllocated>
<PurchaseOrderID>107</PurchaseOrderID>
<InventoryID>108</InventoryID>
</row>
<row>
<ID>56</ID>
<OrderID>48</OrderID>
<Product>Northwind Traders Curry Sauce</Product>
<Quantity>25</Quantity>
<UnitPrice>40</UnitPrice>
<Discount>0</Discount>
<StatusID>Invoiced</StatusID>
<DateAllocated>NULL</DateAllocated>
<PurchaseOrderID>108</PurchaseOrderID>
<InventoryID>106</InventoryID>
</row>
<row>
<ID>57</ID>
<OrderID>48</OrderID>
<Product>Northwind Traders Chocolate Biscuits Mix</Product>
<Quantity>25</Quantity>
<UnitPrice>9.2</UnitPrice>
<Discount>0</Discount>
<StatusID>Invoiced</StatusID>
<DateAllocated>NULL</DateAllocated>
<PurchaseOrderID>109</PurchaseOrderID>
<InventoryID>112</InventoryID>
</row>
<row>
<ID>59</ID>
<OrderID>50</OrderID>
<Product>Northwind Traders Scones</Product>
<Quantity>20</Quantity>
<UnitPrice>10</UnitPrice>
<Discount>0</Discount>
<StatusID>Invoiced</StatusID>
<DateAllocated>NULL</DateAllocated>
<PurchaseOrderID>NULL</PurchaseOrderID>
<InventoryID>92</InventoryID>
</row>
<row>
<ID>60</ID>
<OrderID>51</OrderID>
<Product>Northwind Traders Olive Oil</Product>
<Quantity>25</Quantity>
<UnitPrice>21.35</UnitPrice>
<Discount>0</Discount>
<StatusID>Invoiced</StatusID>
<DateAllocated>NULL</DateAllocated>
<PurchaseOrderID>NULL</PurchaseOrderID>
<InventoryID>93</InventoryID>
</row>
<row>
<ID>61</ID>
<OrderID>51</OrderID>
<Product>Northwind Traders Clam Chowder</Product>
<Quantity>30</Quantity>
<UnitPrice>9.65</UnitPrice>
<Discount>0</Discount>
<StatusID>Invoiced</StatusID>
<DateAllocated>NULL</DateAllocated>
<PurchaseOrderID>NULL</PurchaseOrderID>
<InventoryID>94</InventoryID>
</row>
<row>
<ID>62</ID>
<OrderID>51</OrderID>
<Product>Northwind Traders Crab Meat</Product>
<Quantity>30</Quantity>
<UnitPrice>18.4</UnitPrice>
<Discount>0</Discount>
<StatusID>Invoiced</StatusID>
<DateAllocated>NULL</DateAllocated>
<PurchaseOrderID>NULL</PurchaseOrderID>
<InventoryID>95</InventoryID>
</row>
<row>
<ID>66</ID>
<OrderID>56</OrderID>
<Product>Northwind Traders Chocolate</Product>
<Quantity>10</Quantity>
<UnitPrice>12.75</UnitPrice>
<Discount>0</Discount>
<StatusID>Invoiced</StatusID>
<DateAllocated>NULL</DateAllocated>
<PurchaseOrderID>111</PurchaseOrderID>
<InventoryID>99</InventoryID>
</row>
<row>
<ID>67</ID>
<OrderID>55</OrderID>
<Product>Northwind Traders Beer</Product>
<Quantity>87</Quantity>
<UnitPrice>14</UnitPrice>
<Discount>0</Discount>
<StatusID>Invoiced</StatusID>
<DateAllocated>NULL</DateAllocated>
<PurchaseOrderID>NULL</PurchaseOrderID>
<InventoryID>117</InventoryID>
</row>
<row>
<ID>68</ID>
<OrderID>79</OrderID>
<Product>Northwind Traders Dried Pears</Product>
<Quantity>30</Quantity>
<UnitPrice>30</UnitPrice>
<Discount>0</Discount>
<StatusID>Invoiced</StatusID>
<DateAllocated>NULL</DateAllocated>
<PurchaseOrderID>NULL</PurchaseOrderID>
<InventoryID>119</InventoryID>
</row>
<row>
<ID>69</ID>
<OrderID>79</OrderID>
<Product>Northwind Traders Dried Apples</Product>
<Quantity>30</Quantity>
<UnitPrice>53</UnitPrice>
<Discount>0</Discount>
<StatusID>Invoiced</StatusID>
<DateAllocated>NULL</DateAllocated>
<PurchaseOrderID>NULL</PurchaseOrderID>
<InventoryID>118</InventoryID>
</row>
<row>
<ID>70</ID>
<OrderID>78</OrderID>
<Product>Northwind Traders Fruit Cocktail</Product>
<Quantity>40</Quantity>
<UnitPrice>39</UnitPrice>
<Discount>0</Discount>
<StatusID>Invoiced</StatusID>
<DateAllocated>NULL</DateAllocated>
<PurchaseOrderID>NULL</PurchaseOrderID>
<InventoryID>120</InventoryID>
</row>
<row>
<ID>71</ID>
<OrderID>77</OrderID>
<Product>Northwind Traders Boysenberry Spread</Product>
<Quantity>90</Quantity>
<UnitPrice>25</UnitPrice>
<Discount>0</Discount>
<StatusID>Invoiced</StatusID>
<DateAllocated>NULL</DateAllocated>
<PurchaseOrderID>NULL</PurchaseOrderID>
<InventoryID>121</InventoryID>
</row>
<row>
<ID>72</ID>
<OrderID>76</OrderID>
<Product>Northwind Traders Cajun Seasoning</Product>
<Quantity>30</Quantity>
<UnitPrice>22</UnitPrice>
<Discount>0</Discount>
<StatusID>Invoiced</StatusID>
<DateAllocated>NULL</DateAllocated>
<PurchaseOrderID>NULL</PurchaseOrderID>
<InventoryID>122</InventoryID>
</row>
<row>
<ID>73</ID>
<OrderID>75</OrderID>
<Product>Northwind Traders Chocolate</Product>
<Quantity>40</Quantity>
<UnitPrice>12.75</UnitPrice>
<Discount>0</Discount>
<StatusID>Invoiced</StatusID>
<DateAllocated>NULL</DateAllocated>
<PurchaseOrderID>NULL</PurchaseOrderID>
<InventoryID>123</InventoryID>
</row>
<row>
<ID>74</ID>
<OrderID>74</OrderID>
<Product>Northwind Traders Chocolate</Product>
<Quantity>40</Quantity>
<UnitPrice>12.75</UnitPrice>
<Discount>0</Discount>
<StatusID>Invoiced</StatusID>
<DateAllocated>NULL</DateAllocated>
<PurchaseOrderID>NULL</PurchaseOrderID>
<InventoryID>124</InventoryID>
</row>
<row>
<ID>75</ID>
<OrderID>73</OrderID>
<Product>Northwind Traders Clam Chowder</Product>
<Quantity>10</Quantity>
<UnitPrice>9.65</UnitPrice>
<Discount>0</Discount>
<StatusID>Invoiced</StatusID>
<DateAllocated>NULL</DateAllocated>
<PurchaseOrderID>NULL</PurchaseOrderID>
<InventoryID>125</InventoryID>
</row>
<row>
<ID>76</ID>
<OrderID>72</OrderID>
<Product>Northwind Traders Coffee</Product>
<Quantity>5</Quantity>
<UnitPrice>46</UnitPrice>
<Discount>0</Discount>
<StatusID>Invoiced</StatusID>
<DateAllocated>NULL</DateAllocated>
<PurchaseOrderID>NULL</PurchaseOrderID>
<InventoryID>126</InventoryID>
</row>
<row>
<ID>77</ID>
<OrderID>71</OrderID>
<Product>Northwind Traders Crab Meat</Product>
<Quantity>40</Quantity>
<UnitPrice>18.4</UnitPrice>
<Discount>0</Discount>
<StatusID>Invoiced</StatusID>
<DateAllocated>NULL</DateAllocated>
<PurchaseOrderID>NULL</PurchaseOrderID>
<InventoryID>127</InventoryID>
</row>
<row>
<ID>78</ID>
<OrderID>70</OrderID>
<Product>Northwind Traders Curry Sauce</Product>
<Quantity>20</Quantity>
<UnitPrice>40</UnitPrice>
<Discount>0</Discount>
<StatusID>Invoiced</StatusID>
<DateAllocated>NULL</DateAllocated>
<PurchaseOrderID>NULL</PurchaseOrderID>
<InventoryID>128</InventoryID>
</row>
<row>
<ID>79</ID>
<OrderID>69</OrderID>
<Product>Northwind Traders Dried Plums</Product>
<Quantity>15</Quantity>
<UnitPrice>3.5</UnitPrice>
<Discount>0</Discount>
<StatusID>Invoiced</StatusID>
<DateAllocated>NULL</DateAllocated>
<PurchaseOrderID>NULL</PurchaseOrderID>
<InventoryID>129</InventoryID>
</row>
<row>
<ID>80</ID>
<OrderID>67</OrderID>
<Product>Northwind Traders Almonds</Product>
<Quantity>20</Quantity>
<UnitPrice>10</UnitPrice>
<Discount>0</Discount>
<StatusID>Invoiced</StatusID>
<DateAllocated>NULL</DateAllocated>
<PurchaseOrderID>NULL</PurchaseOrderID>
<InventoryID>130</InventoryID>
</row>
<row>
<ID>81</ID>
<OrderID>60</OrderID>
<Product>Northwind Traders Mozzarella</Product>
<Quantity>40</Quantity>
<UnitPrice>34.8</UnitPrice>
<Discount>0</Discount>
<StatusID>Invoiced</StatusID>
<DateAllocated>NULL</DateAllocated>
<PurchaseOrderID>NULL</PurchaseOrderID>
<InventoryID>131</InventoryID>
</row>
<row>
<ID>82</ID>
<OrderID>63</OrderID>
<Product>Northwind Traders Syrup</Product>
<Quantity>50</Quantity>
<UnitPrice>10</UnitPrice>
<Discount>0</Discount>
<StatusID>Invoiced</StatusID>
<DateAllocated>NULL</DateAllocated>
<PurchaseOrderID>NULL</PurchaseOrderID>
<InventoryID>132</InventoryID>
</row>
<row>
<ID>83</ID>
<OrderID>63</OrderID>
<Product>Northwind Traders Curry Sauce</Product>
<Quantity>3</Quantity>
<UnitPrice>40</UnitPrice>
<Discount>0</Discount>
<StatusID>Invoiced</StatusID>
<DateAllocated>NULL</DateAllocated>
<PurchaseOrderID>NULL</PurchaseOrderID>
<InventoryID>133</InventoryID>
</row>
<row>
<ID>84</ID>
<OrderID>58</OrderID>
<Product>Northwind Traders Marmalade</Product>
<Quantity>40</Quantity>
<UnitPrice>81</UnitPrice>
<Discount>0</Discount>
<StatusID>Invoiced</StatusID>
<DateAllocated>NULL</DateAllocated>
<PurchaseOrderID>NULL</PurchaseOrderID>
<InventoryID>134</InventoryID>
</row>
<row>
<ID>85</ID>
<OrderID>58</OrderID>
<Product>Northwind Traders Long Grain Rice</Product>
<Quantity>40</Quantity>
<UnitPrice>7</UnitPrice>
<Discount>0</Discount>
<StatusID>Invoiced</StatusID>
<DateAllocated>NULL</DateAllocated>
<PurchaseOrderID>NULL</PurchaseOrderID>
<InventoryID>135</InventoryID>
</row>
<row>
<ID>86</ID>
<OrderID>80</OrderID>
<Product>Northwind Traders Gnocchi</Product>
<Quantity>10</Quantity>
<UnitPrice>38</UnitPrice>
<Discount>0</Discount>
<StatusID>Allocated</StatusID>
<DateAllocated>NULL</DateAllocated>
<PurchaseOrderID>NULL</PurchaseOrderID>
<InventoryID>136</InventoryID>
</row>
<row>
<ID>90</ID>
<OrderID>81</OrderID>
<Product>Northwind Traders Green Tea</Product>
<Quantity>0</Quantity>
<UnitPrice>2.99</UnitPrice>
<Discount>0</Discount>
<StatusID>No Stock</StatusID>
<DateAllocated>NULL</DateAllocated>
<PurchaseOrderID>NULL</PurchaseOrderID>
<InventoryID>NULL</InventoryID>
</row>
<row>
<ID>91</ID>
<OrderID>81</OrderID>
<Product>Northwind Traders Gnocchi</Product>
<Quantity>0</Quantity>
<UnitPrice>38</UnitPrice>
<Discount>0</Discount>
<StatusID>None</StatusID>
<DateAllocated>NULL</DateAllocated>
<PurchaseOrderID>NULL</PurchaseOrderID>
<InventoryID>NULL</InventoryID>
</row>
</test></root>